README.md
pyproject.toml
shamela2epub/__init__.py
shamela2epub/__main__.py
shamela2epub/assets/NotoNaskhArabic-Regular.ttf
shamela2epub/assets/books-duotone-128.png
shamela2epub/assets/books-duotone-512.png
shamela2epub/assets/books-duotone.ico
shamela2epub/assets/books-duotone.svg
shamela2epub/assets/download-duotone-64.png
shamela2epub/assets/download-duotone.svg
shamela2epub/assets/styles.css
shamela2epub/cli/__init__.py
shamela2epub/cli/app.py
shamela2epub/gui/__init__.py
shamela2epub/gui/app.py
shamela2epub/gui/ui.ui
shamela2epub/main.py
shamela2epub/misc/__init__.py
shamela2epub/misc/constants.py
shamela2epub/misc/http.py
shamela2epub/misc/patterns.py
shamela2epub/misc/utils.py
shamela2epub/models/__init__.py
shamela2epub/models/book_base_html_page.py
shamela2epub/models/book_html_page.py
shamela2epub/models/book_info_html_page.py
shamela2epub/models/epub_book.py
shamela2epub-1.4.2.dist-info/LICENSE
shamela2epub-1.4.2.dist-info/METADATA
shamela2epub-1.4.2.dist-info/WHEEL
shamela2epub-1.4.2.dist-info/entry_points.txt
shamela2epub-1.4.2.dist-info/RECORD
