Metadata-Version: 2.1
Name: shamela2epub
Version: 1.4.2
Summary: A CLI and GUI tool to download a book on https://shamela.ws to an EPUB book.
Home-page: https://github.com/yshalsager/shamela2epub/
License: GPL-3.0-only
Keywords: epub3,shamela,book,epub,islamic
Author: yshalsager
Author-email: ysh-alsager@hotmail.com
Requires-Python: >=3.12,<3.13
Classifier: License :: OSI Approved :: GNU General Public License v3 (GPLv3)
Classifier: Programming Language :: Python :: 3
Classifier: Programming Language :: Python :: 3.12
Requires-Dist: EbookLib (>=0.17.1,<0.19.0)
Requires-Dist: click (>=8.1.7,<9.0.0)
Requires-Dist: lxml (>=5.1.0,<6.0.0)
Requires-Dist: niquests (>=3.5.3,<4.0.0)
Requires-Dist: parsel (>=1.9.0,<2.0.0)
Requires-Dist: tomli (>=2.0.1,<3.0.0)
Requires-Dist: tqdm (>=4.65.0,<5.0.0)
Requires-Dist: trogon (>=0.5.0,<0.6.0)
Project-URL: Repository, https://github.com/yshalsager/shamela2epub/
